compendium/__init__.py
compendium/config_manager.py
compendium/exceptions.py
compendium/filepaths.py
compendium/loader.py
compendium/py.typed
compendium/settings.py
compendium/filetypes/__init__.py
compendium/filetypes/ini.py
compendium/filetypes/json.py
compendium/filetypes/toml.py
compendium/filetypes/xml.py
compendium/filetypes/yaml.py
compendium-0.1.4.dist-info/METADATA
compendium-0.1.4.dist-info/WHEEL
compendium-0.1.4.dist-info/licenses/LICENSE
compendium-0.1.4.dist-info/RECORD
