Metadata-Version: 2.4
Name: compendium
Version: 0.1.4
Summary: Simple layered configuraion tool
Project-URL: homepage, https://github.com/kuwv/python-compendium
Project-URL: documentation, https://kuwv.github.io/python-compendium
Author-email: "Jesse P. Johnson" <jpj6652@gmail.com>
Maintainer-email: "Jesse P. Johnson" <jpj6652@gmail.com>
License:                                  Apache License
License-File: LICENSE
Keywords: configuration,configuration management
Classifier: Development Status :: 5 - Production/Stable
Classifier: Intended Audience :: Developers
Classifier: License :: OSI Approved :: Apache Software License
Classifier: Programming Language :: Python
Classifier: Programming Language :: Python :: 3
Classifier: Programming Language :: Python :: 3.6
Classifier: Programming Language :: Python :: 3.7
Classifier: Programming Language :: Python :: 3.8
Classifier: Programming Language :: Python :: 3.9
Classifier: Programming Language :: Python :: 3.10
Classifier: Programming Language :: Python :: 3.11
Classifier: Programming Language :: Python :: 3.12
Classifier: Topic :: Software Development :: Libraries
Requires-Python: >=3.6.2
Requires-Dist: anytree>=2.8.0
Requires-Dist: dpath>=2.0.1
Requires-Dist: ruamel-yaml<1,>=0.16.10
Requires-Dist: tomlkit<1,>=0.7.0
Provides-Extra: build
Requires-Dist: build; extra == 'build'
Requires-Dist: invoke>=1.4.1; extra == 'build'
Requires-Dist: proman-versioning<1,>=0.1.1-beta.4; extra == 'build'
Requires-Dist: proman-workflows<1,>=0.1.0a8; extra == 'build'
Provides-Extra: dev
Requires-Dist: bandit>=1.6.2; extra == 'dev'
Requires-Dist: black>=24.1.0; extra == 'dev'
Requires-Dist: flake8>=3.8.2; extra == 'dev'
Requires-Dist: isort[pyproject]>=4.3.21; extra == 'dev'
Requires-Dist: mypy-extensions>=0.4.3; extra == 'dev'
Requires-Dist: mypy>=1; extra == 'dev'
Requires-Dist: pyfakefs>=5.4.1; extra == 'dev'
Requires-Dist: pylint>=2.9.5; extra == 'dev'
Requires-Dist: pytest-cov>=2.9.0; extra == 'dev'
Requires-Dist: pytest>=6.2.5; extra == 'dev'
Requires-Dist: safety>=2.2.0; extra == 'dev'
Provides-Extra: docs
Requires-Dist: docstr-coverage<2,>=1.2.0; extra == 'docs'
Requires-Dist: mkdocs-material<10,>=9; extra == 'docs'
Requires-Dist: mkdocs<2,>=1.2.2; extra == 'docs'
Requires-Dist: mkdocstrings[python]>=0.16.2; extra == 'docs'
Requires-Dist: pydocstyle[toml]>=6.1.1; extra == 'docs'
Provides-Extra: xml
Requires-Dist: xmltodict<1,>=0.12.0; extra == 'xml'
